AlfonsIoT/__init__.py
AlfonsIoT/main.py
AlfonsIoT-0.0.1.dist-info/METADATA
AlfonsIoT-0.0.1.dist-info/RECORD
AlfonsIoT-0.0.1.dist-info/WHEEL
AlfonsIoT-0.0.1.dist-info/top_level.txt
