Metadata-Version: 2.1
Name: AlfonsIoT
Version: 0.0.1
Summary: A package for IoT's to interact with Alfons
Home-page: https://github.com/ntoonio/AlfonsIoT.git
Author: Anton Lindroth
Author-email: ntoonio@gmail.com
License: UNKNOWN
Platform: UNKNOWN
